wphelper/__init__.py
wphelper/app.py
wphelper/cmds/__init__.py
wphelper/cmds/base.py
wphelper/cmds/post.py
wphelper-0.1.0.dist-info/DESCRIPTION.rst
wphelper-0.1.0.dist-info/METADATA
wphelper-0.1.0.dist-info/RECORD
wphelper-0.1.0.dist-info/WHEEL
wphelper-0.1.0.dist-info/entry_points.txt
wphelper-0.1.0.dist-info/metadata.json
wphelper-0.1.0.dist-info/pbr.json
wphelper-0.1.0.dist-info/top_level.txt
