Metadata-Version: 2.0
Name: wphelper
Version: 0.1.0
Summary: Tools for working with WordPress as a blog author.
Home-page: https://pypi.python.org/pypi/wphelper
Author: Doug Hellmann
Author-email: doug@doughellmann.com
License: UNKNOWN
Platform: UNKNOWN
Classifier: Development Status :: 3 - Alpha
Classifier: Environment :: Console
Classifier: License :: OSI Approved :: Apache Software License
Classifier: Operating System :: POSIX
Classifier: Programming Language :: Python
Classifier: Programming Language :: Python :: 3
Classifier: Programming Language :: Python :: 3.4
Classifier: Topic :: Communications
Requires-Dist: pbr (>=1.0)
Requires-Dist: python-wordpress-xmlrpc (>=2.2)
Requires-Dist: cliff (>=1.14.0)
Requires-Dist: Markdown (>=2.2.1)
